mfprocess/__init__.py
mfprocess/data/__init__.py
mfprocess/data/agus.py
mfprocess/mes/__init__.py
mfprocess/mes/tests.py
mfprocess-1.0.30.dist-info/LICENCE
mfprocess-1.0.30.dist-info/METADATA
mfprocess-1.0.30.dist-info/WHEEL
mfprocess-1.0.30.dist-info/top_level.txt
mfprocess-1.0.30.dist-info/RECORD
