Metadata-Version: 2.1
Name: mfprocess
Version: 1.0.30
Summary: Data Process
Home-page: https://github.com/agustinbustosbarton/mfprocess
Author: Agustin Bustos Barton
Author-email: agustinbustosbarton@gmail.com
Keywords: pypi,cicd,python
Classifier: Development Status :: 1 - Planning
Classifier: Intended Audience :: Developers
Classifier: Programming Language :: Python :: 3
Classifier: Operating System :: Unix
Classifier: Operating System :: MacOS :: MacOS X
Classifier: Operating System :: Microsoft :: Windows
License-File: LICENCE
Requires-Dist: numpy
Requires-Dist: pandas
Requires-Dist: pycountry
Requires-Dist: pyreadstat
Requires-Dist: openai ==0.28.1
Requires-Dist: dateparser
Requires-Dist: pyvis
